rambaldi/__init__.py
rambaldi-2.2.0.dist-info/entry_points.txt
rambaldi-2.2.0.dist-info/WHEEL
rambaldi-2.2.0.dist-info/METADATA
rambaldi-2.2.0.dist-info/RECORD
